projects/fpga-spi/spi_slave.v
/*
 * spi_slave.v — Receives one byte via SPI, outputs it when complete
 *
 * Pure logic, no hard IP. Testable in any simulator.
 */
module spi_slave (
    input  clk,         // system clock (faster than SPI clock)
    input  spi_clk,     // SPI clock from master
    input  spi_mosi,    // data from master
    input  spi_cs,      // chip select (active low)
    output [7:0] data,  // received byte
    output valid        // pulses high for 1 cycle when byte is ready
);
    // Synchronize SPI clock to system clock domain (avoid metastability)
    // 3 stages: [0] might be metastable, [1] is clean, [2] is previous clean
    reg [2:0] sclk_sync = 0;
    always @(posedge clk)
        sclk_sync <= {sclk_sync[1:0], spi_clk};
    wire sclk_rise = (sclk_sync[2:1] == 2'b01);  // edge detect on clean bits only

    // Shift register — shifts in one bit per SPI clock rising edge
    reg [7:0] shift = 0;
    reg [2:0] bit_count = 0;
    reg       byte_valid = 0;

    always @(posedge clk) begin
        byte_valid <= 0;
        if (spi_cs) begin
            // CS high = deselected, reset
            bit_count <= 0;
        end else if (sclk_rise) begin
            // Shift in one bit (MSB first)
            shift <= {shift[6:0], spi_mosi};
            bit_count <= bit_count + 1;
            if (bit_count == 7) begin
                byte_valid <= 1;  // full byte received
            end
        end
    end

    assign data = shift;
    assign valid = byte_valid;
endmodule

projects/fpga-spi/tb_spi_slave.v
/*
 * tb_spi_slave.v — Testbench: send bytes over SPI, verify reception
 */
`timescale 1ns/1ps

module tb_spi_slave;
    reg clk = 0;
    always #41.67 clk = ~clk;  // 12MHz system clock

    reg spi_clk = 0;
    reg spi_mosi = 0;
    reg spi_cs = 1;            // deselected initially

    wire [7:0] data;
    wire valid;

    spi_slave uut (
        .clk(clk),
        .spi_clk(spi_clk),
        .spi_mosi(spi_mosi),
        .spi_cs(spi_cs),
        .data(data),
        .valid(valid)
    );

    integer failures = 0;

    // Task: send one byte over SPI (MSB first)
    task spi_send_byte(input [7:0] byte_val);
        integer i;
        begin
            for (i = 7; i >= 0; i = i - 1) begin
                spi_mosi = byte_val[i];
                #500;               // setup time
                spi_clk = 1;       // rising edge — slave samples
                #500;               // hold
                spi_clk = 0;       // falling edge
                #500;
            end
        end
    endtask

    initial begin
        $dumpfile("spi_slave.vcd");
        $dumpvars(0, tb_spi_slave);

        // Wait for synchronizer to settle
        #1000;

        // Test 1: send 0xA5
        spi_cs = 0;
        spi_send_byte(8'hA5);
        #2000;  // wait for valid pulse to propagate
        if (data !== 8'hA5) begin
            $display("FAIL: expected 0xA5, got 0x%02X", data);
            failures = failures + 1;
        end

        // Test 2: send 0x3C without releasing CS
        spi_send_byte(8'h3C);
        #2000;
        if (data !== 8'h3C) begin
            $display("FAIL: expected 0x3C, got 0x%02X", data);
            failures = failures + 1;
        end

        // Test 3: release CS, re-select, send 0xFF
        spi_cs = 1;
        #2000;
        spi_cs = 0;
        spi_send_byte(8'hFF);
        #2000;
        if (data !== 8'hFF) begin
            $display("FAIL: expected 0xFF, got 0x%02X", data);
            failures = failures + 1;
        end

        if (failures == 0)
            $display("PASS: all SPI tests passed");
        else
            $display("FAILED: %0d test(s) failed", failures);

        $finish;
    end
endmodule

projects/fpga-spi/spi_slave.vcd
$date
	Wed May  6 20:38:47 2026
$end
$version
	Icarus Verilog
$end
$timescale
	1ps
$end
$scope module tb_spi_slave $end
$var wire 1 ! valid $end
$var wire 8 " data [7:0] $end
$var reg 1 # clk $end
$var reg 1 $ spi_clk $end
$var reg 1 % spi_cs $end
$var reg 1 & spi_mosi $end
$var integer 32 ' failures [31:0] $end
$scope module uut $end
$var wire 1 # clk $end
$var wire 8 ( data [7:0] $end
$var wire 1 $ spi_clk $end
$var wire 1 % spi_cs $end
$var wire 1 & spi_mosi $end
$var wire 1 ! valid $end
$var wire 1 ) sclk_rise $end
$var reg 3 * bit_count [2:0] $end
$var reg 1 + byte_valid $end
$var reg 3 , sclk_sync [2:0] $end
$var reg 8 - shift [7:0] $end
$upscope $end
$scope task spi_send_byte $end
$var reg 8 . byte_val [7:0] $end
$var integer 32 / i [31:0] $end
$upscope $end
$upscope $end
$enddefinitions $end
$comment Show the parameter values. $end
$dumpall
$end
#0
$dumpvars
bx /
bx .
b0 -
b0 ,
0+
b0 *
0)
b0 (
b0 '
0&
1%
0$
0#
b0 "
0!
$end
#41670
1#
#83340
0#
#125010
1#
#166680
0#
#208350
1#
#250020
0#
#291690
1#
#333360
0#
#375030
1#
#416700
0#
#458370
1#
#500040
0#
#541710
1#
#583380
0#
#625050
1#
#666720
0#
#708390
1#
#750060
0#
#791730
1#
#833400
0#
#875070
1#
#916740
0#
#958410
1#
#1000000
1&
b111 /
b10100101 .
0%
#1000080
0#
#1041750
1#
#1083420
0#
#1125090
1#
#1166760
0#
#1208430
1#
#1250100
0#
#1291770
1#
#1333440
0#
#1375110
1#
#1416780
0#
#1458450
1#
#1500000
1$
#1500120
0#
#1541790
b1 ,
1#
#1583460
0#
#1625130
1)
b11 ,
1#
#1666800
0#
#1708470
0)
b111 ,
b1 *
b1 "
b1 (
b1 -
1#
#1750140
0#
#1791810
1#
#1833480
0#
#1875150
1#
#1916820
0#
#1958490
1#
#2000000
0$
#2000160
0#
#2041830
b110 ,
1#
#2083500
0#
#2125170
b100 ,
1#
#2166840
0#
#2208510
b0 ,
1#
#2250180
0#
#2291850
1#
#2333520
0#
#2375190
1#
#2416860
0#
#2458530
1#
#2500000
0&
b110 /
#2500200
0#
#2541870
1#
#2583540
0#
#2625210
1#
#2666880
0#
#2708550
1#
#2750220
0#
#2791890
1#
#2833560
0#
#2875230
1#
#2916900
0#
#2958570
1#
#3000000
1$
#3000240
0#
#3041910
b1 ,
1#
#3083580
0#
#3125250
1)
b11 ,
1#
#3166920
0#
#3208590
0)
b111 ,
b10 *
b10 "
b10 (
b10 -
1#
#3250260
0#
#3291930
1#
#3333600
0#
#3375270
1#
#3416940
0#
#3458610
1#
#3500000
0$
#3500280
0#
#3541950
b110 ,
1#
#3583620
0#
#3625290
b100 ,
1#
#3666960
0#
#3708630
b0 ,
1#
#3750300
0#
#3791970
1#
#3833640
0#
#3875310
1#
#3916980
0#
#3958650
1#
#4000000
1&
b101 /
#4000320
0#
#4041990
1#
#4083660
0#
#4125330
1#
#4167000
0#
#4208670
1#
#4250340
0#
#4292010
1#
#4333680
0#
#4375350
1#
#4417020
0#
#4458690
1#
#4500000
1$
#4500360
0#
#4542030
b1 ,
1#
#4583700
0#
#4625370
1)
b11 ,
1#
#4667040
0#
#4708710
0)
b111 ,
b11 *
b101 "
b101 (
b101 -
1#
#4750380
0#
#4792050
1#
#4833720
0#
#4875390
1#
#4917060
0#
#4958730
1#
#5000000
0$
#5000400
0#
#5042070
b110 ,
1#
#5083740
0#
#5125410
b100 ,
1#
#5167080
0#
#5208750
b0 ,
1#
#5250420
0#
#5292090
1#
#5333760
0#
#5375430
1#
#5417100
0#
#5458770
1#
#5500000
0&
b100 /
#5500440
0#
#5542110
1#
#5583780
0#
#5625450
1#
#5667120
0#
#5708790
1#
#5750460
0#
#5792130
1#
#5833800
0#
#5875470
1#
#5917140
0#
#5958810
1#
#6000000
1$
#6000480
0#
#6042150
b1 ,
1#
#6083820
0#
#6125490
1)
b11 ,
1#
#6167160
0#
#6208830
0)
b111 ,
b100 *
b1010 "
b1010 (
b1010 -
1#
#6250500
0#
#6292170
1#
#6333840
0#
#6375510
1#
#6417180
0#
#6458850
1#
#6500000
0$
#6500520
0#
#6542190
b110 ,
1#
#6583860
0#
#6625530
b100 ,
1#
#6667200
0#
#6708870
b0 ,
1#
#6750540
0#
#6792210
1#
#6833880
0#
#6875550
1#
#6917220
0#
#6958890
1#
#7000000
b11 /
#7000560
0#
#7042230
1#
#7083900
0#
#7125570
1#
#7167240
0#
#7208910
1#
#7250580
0#
#7292250
1#
#7333920
0#
#7375590
1#
#7417260
0#
#7458930
1#
#7500000
1$
#7500600
0#
#7542270
b1 ,
1#
#7583940
0#
#7625610
1)
b11 ,
1#
#7667280
0#
#7708950
0)
b111 ,
b101 *
b10100 "
b10100 (
b10100 -
1#
#7750620
0#
#7792290
1#
#7833960
0#
#7875630
1#
#7917300
0#
#7958970
1#
#8000000
0$
#8000640
0#
#8042310
b110 ,
1#
#8083980
0#
#8125650
b100 ,
1#
#8167320
0#
#8208990
b0 ,
1#
#8250660
0#
#8292330
1#
#8334000
0#
#8375670
1#
#8417340
0#
#8459010
1#
#8500000
1&
b10 /
#8500680
0#
#8542350
1#
#8584020
0#
#8625690
1#
#8667360
0#
#8709030
1#
#8750700
0#
#8792370
1#
#8834040
0#
#8875710
1#
#8917380
0#
#8959050
1#
#9000000
1$
#9000720
0#
#9042390
b1 ,
1#
#9084060
0#
#9125730
1)
b11 ,
1#
#9167400
0#
#9209070
0)
b111 ,
b110 *
b101001 "
b101001 (
b101001 -
1#
#9250740
0#
#9292410
1#
#9334080
0#
#9375750
1#
#9417420
0#
#9459090
1#
#9500000
0$
#9500760
0#
#9542430
b110 ,
1#
#9584100
0#
#9625770
b100 ,
1#
#9667440
0#
#9709110
b0 ,
1#
#9750780
0#
#9792450
1#
#9834120
0#
#9875790
1#
#9917460
0#
#9959130
1#
#10000000
0&
b1 /
#10000800
0#
#10042470
1#
#10084140
0#
#10125810
1#
#10167480
0#
#10209150
1#
#10250820
0#
#10292490
1#
#10334160
0#
#10375830
1#
#10417500
0#
#10459170
1#
#10500000
1$
#10500840
0#
#10542510
b1 ,
1#
#10584180
0#
#10625850
1)
b11 ,
1#
#10667520
0#
#10709190
0)
b111 ,
b111 *
b1010010 "
b1010010 (
b1010010 -
1#
#10750860
0#
#10792530
1#
#10834200
0#
#10875870
1#
#10917540
0#
#10959210
1#
#11000000
0$
#11000880
0#
#11042550
b110 ,
1#
#11084220
0#
#11125890
b100 ,
1#
#11167560
0#
#11209230
b0 ,
1#
#11250900
0#
#11292570
1#
#11334240
0#
#11375910
1#
#11417580
0#
#11459250
1#
#11500000
1&
b0 /
#11500920
0#
#11542590
1#
#11584260
0#
#11625930
1#
#11667600
0#
#11709270
1#
#11750940
0#
#11792610
1#
#11834280
0#
#11875950
1#
#11917620
0#
#11959290
1#
#12000000
1$
#12000960
0#
#12042630
b1 ,
1#
#12084300
0#
#12125970
1)
b11 ,
1#
#12167640
0#
#12209310
0)
b111 ,
1!
1+
b0 *
b10100101 "
b10100101 (
b10100101 -
1#
#12250980
0#
#12292650
0!
0+
1#
#12334320
0#
#12375990
1#
#12417660
0#
#12459330
1#
#12500000
0$
#12501000
0#
#12542670
b110 ,
1#
#12584340
0#
#12626010
b100 ,
1#
#12667680
0#
#12709350
b0 ,
1#
#12751020
0#
#12792690
1#
#12834360
0#
#12876030
1#
#12917700
0#
#12959370
1#
#13000000
b11111111111111111111111111111111 /
